{ 
    "simulator":{
        "initialPrice":100000,
    "modules":[ 
       { 
          "moduleId":2,
          "moduleRate":"70%",
          "moduleMath":{ 
             "content":"(營業收入合計  -營業成本合計  )/營業收入合計  >現金股利  ",
             "metaList":[ 
                { 
                   "TO":9,
                   "FROM":1,
                   "metaInfo":{ 
                      "date":null,
                      "name":"營業收入合計",
                      "type":"GRID",
                      "rowId":0,
                      "columnId":2
                   }
                },
                { 
                   "TO":18,
                   "FROM":10,
                   "metaInfo":{ 
                      "date":null,
                      "name":"營業成本合計",
                      "type":"GRID",
                      "rowId":0,
                      "columnId":1
                   }
                },
                { 
                   "TO":28,
                   "FROM":20,
                   "metaInfo":{ 
                      "date":null,
                      "name":"營業收入合計",
                      "type":"AVERAGE",
                      "rowId":"header",
                      "columnId":2
                   }
                },
                { 
                   "TO":35,
                   "FROM":29,
                   "metaInfo":{ 
                      "date":null,
                      "name":"現金股利",
                      "type":"GRID",
                      "rowId":0,
                      "columnId":0
                   }
                }
             ]
          },
          "partitionedDataPhases":[ 
             { 
                "stockPrice":10,
                "timeStamp":"2018-06",
                "chipDataList":[ 
                   { 
                      "chipName":"營業收入合計",
                      "value":"233276811"
                   },
                   { 
                      "chipName":"營業成本合計",
                      "value":"121688707"
                   },
                   { 
                      "chipName":"營業收入合計",
                      "value":"233276811"
                   },
                   { 
                      "chipName":"現金股利",
                      "value":"48941318"
                   }
                ]
             },
             { 
                "stockPrice":10,
                "timeStamp":"2018-09",
                "chipDataList":[ 
                   { 
                      "chipName":"營業收入合計",
                      "value":"260347882"
                   },
                   { 
                      "chipName":"營業成本合計",
                      "value":"136967039"
                   },
                   { 
                      "chipName":"營業收入合計",
                      "value":"260347882"
                   },
                   { 
                      "chipName":"現金股利",
                      "value":"8494615464135"
                   }
                ]
             },
             { 
                "stockPrice":10,
                "timeStamp":"2018-12",
                "chipDataList":[ 
                   { 
                      "chipName":"營業收入合計",
                      "value":"1031473557"
                   },
                   { 
                      "chipName":"營業成本合計",
                      "value":"533487516"
                   },
                   { 
                      "chipName":"營業收入合計",
                      "value":"1031473557"
                   },
                   { 
                      "chipName":"現金股利",
                      "value":"1541514198"
                   }
                ]
             },
             { 
                "stockPrice":10,
                "timeStamp":"2019-03",
                "chipDataList":[ 
                   { 
                      "chipName":"營業收入合計",
                      "value":"218704469"
                   },
                   { 
                      "chipName":"營業成本合計",
                      "value":"128352344"
                   },
                   { 
                      "chipName":"營業收入合計",
                      "value":"218704469"
                   },
                   { 
                      "chipName":"現金股利",
                      "value":"78979487"
                   }
                ]
             },
             { 
                "stockPrice":10,
                "timeStamp":"2019-06",
                "chipDataList":[ 
                   { 
                      "chipName":"營業收入合計",
                      "value":"240998475"
                   },
                   { 
                      "chipName":"營業成本合計",
                      "value":"137325245"
                   },
                   { 
                      "chipName":"營業收入合計",
                      "value":"240998475"
                   },
                   { 
                      "chipName":"現金股利",
                      "value":"894849842"
                   }
                ]
             }
          ],
          "gridTypePastData":[ 
             { 
                "chipName":"營業收入合計",
                "data":[ 
                   { 
                      "timeStamp":"2018-03",
                      "value":"248078671"
                   },
                   { 
                      "timeStamp":"2017-12",
                      "value":"89484842"
                   }
                ]
             },
             { 
                "chipName":"營業成本合計",
                "data":[ 
                   { 
                      "timeStamp":"2018-03",
                      "value":"123103977"
                   },
                   { 
                      "timeStamp":"2017-12",
                      "value":"482616286"
                   }
                ]
             },
             { 
                "chipName":"現金股利",
                "data":[ 
                    { 
                       "timeStamp":"2018-03",
                       "value":"783872783"
                    },
                    { 
                       "timeStamp":"2017-12",
                       "value":"272782878"
                    }
                 ]
             }
          ]
       }
    ]
    }
 }